hayashi/__init__.py
hayashi/constants.py
hayashi/cosmo.py
hayashi/forest.py
hayashi/lss.py
hayashi/nlcdm.py
hayashi/subhalos.py
hayashi/utils.py
hayashi/version.py
hayashi-1.1.6.dist-info/LICENSE
hayashi-1.1.6.dist-info/METADATA
hayashi-1.1.6.dist-info/WHEEL
hayashi-1.1.6.dist-info/top_level.txt
hayashi-1.1.6.dist-info/RECORD
